supersonic_downloader/__init__.py
supersonic_downloader/api.py
supersonic_downloader/supersonic_download.py
supersonic_downloader/utils.py
supersonic_downloader-0.0.1.dist-info/METADATA
supersonic_downloader-0.0.1.dist-info/WHEEL
supersonic_downloader-0.0.1.dist-info/licenses/LICENSE
supersonic_downloader-0.0.1.dist-info/RECORD
