Metadata-Version: 2.3
Name: supersonic_downloader
Version: 0.0.1
Summary: A fast and efficient downloader
Project-URL: Repository, https://github.com/bz-e/supersonic_downloader.git
Author-email: bz-e <bozhang_2@163.com>
Maintainer-email: bz-e <bozhang_2@163.com>
License: MIT License
License-File: LICENSE
Keywords: Async,Coroutine,Downloader,Fast,Multithreading
Classifier: Development Status :: 4 - Beta
Classifier: Programming Language :: Python
Requires-Python: >=3.10
Requires-Dist: aiohttp>=3.10.8
Requires-Dist: loguru>=0.7.2
Requires-Dist: requests>=2.32.3
